{"name":"JS","slug":"JS","count":5,"postlist":[{"title":"Axios详解","uid":"497057504cdf696233ca7859e8edacd2","slug":"Axios详解","date":"2022-10-27T08:09:00.000Z","updated":"2022-10-27T08:11:25.944Z","comments":true,"path":"api/articles/Axios详解.json","keywords":"Love And Freedom","cover":"img/axios.png","text":"Axios基于promise可以用于浏览器和node.js的网络请求库一、基础定义Promise1.promise一个对象，用于传递异步操作的消息；本意上可以理解为，承诺过一段时间返回一个结果。 basic 其实就是一个请求发出去以后，并不能马上获得需要的数据，因此整个js代码需...","link":"","photos":[],"count_time":{"symbolsCount":"13k","symbolsTime":"12 mins."},"categories":[{"name":"JS","slug":"JS","count":2,"path":"api/categories/JS.json"}],"tags":[{"name":"JS","slug":"JS","count":5,"path":"api/tags/JS.json"}],"author":{"name":"Martin","slug":"blog-author","avatar":"https://img-blog.csdnimg.cn/20210313122054101.png","link":"/","description":"Be Myself","socials":{"github":"","twitter":"","stackoverflow":"","wechat":"","qq":"","weibo":"","zhihu":"","csdn":"","juejin":"","customs":{}}}},{"title":"Vue笔记","uid":"51d3872cd56d489d412dadd4338316da","slug":"JS","date":"2022-10-11T18:51:45.000Z","updated":"2023-04-04T13:35:28.254Z","comments":true,"path":"api/articles/JS.json","keywords":"Love And Freedom","cover":"img/vue.png","text":"JS一、各司其职 HTML、CSS、JS职能分离 二、组件封装 好的UI组件具有正确性、拓展性、复用性 1.结构轮播图其实是一个列表结构； 通过css将图片层叠在一起； 2.展现效果3.行为API 功能 Event 控制流：使用自定义的事件来解耦 4.改进空间 解耦+ 三、过程抽...","link":"","photos":[],"count_time":{"symbolsCount":835,"symbolsTime":"1 mins."},"categories":[{"name":"前端","slug":"前端","count":37,"path":"api/categories/前端.json"}],"tags":[{"name":"笔记","slug":"笔记","count":39,"path":"api/tags/笔记.json"},{"name":"JS","slug":"JS","count":5,"path":"api/tags/JS.json"}],"author":{"name":"Martin","slug":"blog-author","avatar":"https://img-blog.csdnimg.cn/20210313122054101.png","link":"/","description":"Be Myself","socials":{"github":"","twitter":"","stackoverflow":"","wechat":"","qq":"","weibo":"","zhihu":"","csdn":"","juejin":"","customs":{}}}},{"title":"防抖与节流","uid":"cd6a12c0c07e3b04d0fd2533bf4aa0fa","slug":"JS防抖和节流","date":"2023-07-06T05:51:45.000Z","updated":"2023-07-07T02:13:22.364Z","comments":true,"path":"api/articles/JS防抖和节流.json","keywords":"Love And Freedom","cover":"img/bg2.jpg","text":"防抖与节流一、防抖1.应用场景 窗口 resize，滚动条 scroll，输入框 input 持续发生，具有过程的事件 2.应用：利用闭包实现let inputEvent = document.querySelector('input') let content = docume...","link":"","photos":[],"count_time":{"symbolsCount":"1k","symbolsTime":"1 mins."},"categories":[{"name":"JS","slug":"JS","count":2,"path":"api/categories/JS.json"}],"tags":[{"name":"JS","slug":"JS","count":5,"path":"api/tags/JS.json"},{"name":"JS技巧","slug":"JS技巧","count":1,"path":"api/tags/JS技巧.json"}],"author":{"name":"Martin","slug":"blog-author","avatar":"https://img-blog.csdnimg.cn/20210313122054101.png","link":"/","description":"Be Myself","socials":{"github":"","twitter":"","stackoverflow":"","wechat":"","qq":"","weibo":"","zhihu":"","csdn":"","juejin":"","customs":{}}},"feature":true},{"title":"Vue笔记","uid":"51d3872cd56d489d412dadd4338316da","slug":"JS基础","date":"2022-09-11T18:51:45.000Z","updated":"2023-04-04T13:35:41.643Z","comments":true,"path":"api/articles/JS基础.json","keywords":"Love And Freedom","cover":"img/vue.png","text":"JS高级程序设计一、基础基础基础1.基础语法 for-in //for-in语法是一种精准的迭代语句，可以用来枚举对象的属性； for(property in expression)&#123; statement; &#125; for(var propName in wind...","link":"","photos":[],"count_time":{"symbolsCount":"13k","symbolsTime":"12 mins."},"categories":[{"name":"前端","slug":"前端","count":37,"path":"api/categories/前端.json"}],"tags":[{"name":"笔记","slug":"笔记","count":39,"path":"api/tags/笔记.json"},{"name":"JS","slug":"JS","count":5,"path":"api/tags/JS.json"}],"author":{"name":"Martin","slug":"blog-author","avatar":"https://img-blog.csdnimg.cn/20210313122054101.png","link":"/","description":"Be Myself","socials":{"github":"","twitter":"","stackoverflow":"","wechat":"","qq":"","weibo":"","zhihu":"","csdn":"","juejin":"","customs":{}}}},{"title":"Web Audio API","uid":"b9697662cdffe977cb41ca0017dc8bf9","slug":"Web Audio","date":"2023-06-26T13:13:45.000Z","updated":"2023-07-03T09:35:40.499Z","comments":true,"path":"api/articles/Web Audio.json","keywords":"Love And Freedom","cover":"img/bg3.jpg","text":"Web Audio API 实现功能可视化、音色合成器、动态混音、声音特效、3D空间音频、均衡器、环境混响 一、基础使用1.AudioContext为音频处理提供一个上下文环境，相当于一个中央控制器，控制音频路由的各个模块； 1.1音频结点AudioNode音频路由中的基本单位，...","link":"","photos":[],"count_time":{"symbolsCount":456,"symbolsTime":"1 mins."},"categories":[{"name":"前端","slug":"前端","count":37,"path":"api/categories/前端.json"}],"tags":[{"name":"笔记","slug":"笔记","count":39,"path":"api/tags/笔记.json"},{"name":"JS","slug":"JS","count":5,"path":"api/tags/JS.json"},{"name":"TS","slug":"TS","count":2,"path":"api/tags/TS.json"}],"author":{"name":"Martin","slug":"blog-author","avatar":"https://img-blog.csdnimg.cn/20210313122054101.png","link":"/","description":"Be Myself","socials":{"github":"","twitter":"","stackoverflow":"","wechat":"","qq":"","weibo":"","zhihu":"","csdn":"","juejin":"","customs":{}}}}]}