{"name":"面试笔记","slug":"面试笔记","count":4,"postlist":[{"title":"前端开发调试","uid":"758ca3435563534b448be7a72bef9969","slug":"前端开发调试","date":"2023-03-27T10:51:45.000Z","updated":"2023-03-27T11:06:48.816Z","comments":true,"path":"api/articles/前端开发调试.json","keywords":"Love And Freedom","cover":"img/bg14.jpg","text":"前端开发调试 No code，no bug 一、Bug 与 Debug1.前端Debug的特点 多平台（浏览器、NodeJS、） 多环境（本地开发环境，线上环境） 多工具（Chrome Devtools、Charles、） 多技巧（Console、Breakpoint、sourc...","link":"","photos":[],"count_time":{"symbolsCount":"1.8k","symbolsTime":"2 mins."},"categories":[{"name":"前端","slug":"前端","count":37,"path":"api/categories/前端.json"}],"tags":[{"name":"笔记","slug":"笔记","count":39,"path":"api/tags/笔记.json"},{"name":"面试笔记","slug":"面试笔记","count":4,"path":"api/tags/面试笔记.json"}],"author":{"name":"Martin","slug":"blog-author","avatar":"https://img-blog.csdnimg.cn/20210313122054101.png","link":"/","description":"Be Myself","socials":{"github":"","twitter":"","stackoverflow":"","wechat":"","qq":"","weibo":"","zhihu":"","csdn":"","juejin":"","customs":{}}}},{"title":"前端监控SDK","uid":"ff3c421ef1d9934b79c84f7fecbba276","slug":"前端监控SDK","date":"2023-03-27T10:51:45.000Z","updated":"2023-03-27T11:06:37.681Z","comments":true,"path":"api/articles/前端监控SDK.json","keywords":"Love And Freedom","cover":"img/bg13.jpg","text":"前端监控SDK一、为什么要聊前端监控？1.经典面试题 Q：在浏览器里，从输入url到页面展示，这中间发生了什么？ 浏览网页出现的问题 打开缓慢（使用的xp+ie，建议升级系统） 卡顿（电脑配置太差，建议升级硬件） 图片裂开（用户网络太差，建议升级宽带） 白屏（在我电脑上没问题啊！...","link":"","photos":[],"count_time":{"symbolsCount":"1.2k","symbolsTime":"1 mins."},"categories":[{"name":"前端","slug":"前端","count":37,"path":"api/categories/前端.json"}],"tags":[{"name":"笔记","slug":"笔记","count":39,"path":"api/tags/笔记.json"},{"name":"面试笔记","slug":"面试笔记","count":4,"path":"api/tags/面试笔记.json"}],"author":{"name":"Martin","slug":"blog-author","avatar":"https://img-blog.csdnimg.cn/20210313122054101.png","link":"/","description":"Be Myself","socials":{"github":"","twitter":"","stackoverflow":"","wechat":"","qq":"","weibo":"","zhihu":"","csdn":"","juejin":"","customs":{}}}},{"title":"前端面筋","uid":"ea16d4275e7521767b51128cd8bf6cd4","slug":"前端面经","date":"2023-03-27T10:51:45.000Z","updated":"2023-05-25T12:53:43.059Z","comments":true,"path":"api/articles/前端面经.json","keywords":"Love And Freedom","cover":"img/bg11.jpg","text":"前端三大件一、HTML二、CSS1.Flex布局 Flex布局包括容器和Item两部分；一个容器的所有子元素都成为他的item成员； flex-direction:主轴方向，row，row-reverse，column，column-recerse； flex-wrap:默认所有...","link":"","photos":[],"count_time":{"symbolsCount":"20k","symbolsTime":"18 mins."},"categories":[{"name":"前端","slug":"前端","count":37,"path":"api/categories/前端.json"}],"tags":[{"name":"笔记","slug":"笔记","count":39,"path":"api/tags/笔记.json"},{"name":"面试笔记","slug":"面试笔记","count":4,"path":"api/tags/面试笔记.json"}],"author":{"name":"Martin","slug":"blog-author","avatar":"https://img-blog.csdnimg.cn/20210313122054101.png","link":"/","description":"Be Myself","socials":{"github":"","twitter":"","stackoverflow":"","wechat":"","qq":"","weibo":"","zhihu":"","csdn":"","juejin":"","customs":{}}}},{"title":"跨端技术概述","uid":"9e5c5d85c6ecb493e815e549e0c2b04d","slug":"跨端技术概述","date":"2023-03-27T10:51:45.000Z","updated":"2023-03-27T11:07:06.979Z","comments":true,"path":"api/articles/跨端技术概述.json","keywords":"Love And Freedom","cover":"img/bg15.jpg","text":"跨端技术概述一、跨端是什么？1.跨端背景 PC端（Windows,Mac） 移动端（iOS，Android） Web端 IoT端（车载设备，穿戴设备） 2.常见痛点 各端功能几乎一致，各端需要单独配置开发人员； 开发、维护成本高； 安卓、IOS发版周期长； … 3.跨端技术方案目...","link":"","photos":[],"count_time":{"symbolsCount":665,"symbolsTime":"1 mins."},"categories":[{"name":"前端","slug":"前端","count":37,"path":"api/categories/前端.json"}],"tags":[{"name":"笔记","slug":"笔记","count":39,"path":"api/tags/笔记.json"},{"name":"面试笔记","slug":"面试笔记","count":4,"path":"api/tags/面试笔记.json"}],"author":{"name":"Martin","slug":"blog-author","avatar":"https://img-blog.csdnimg.cn/20210313122054101.png","link":"/","description":"Be Myself","socials":{"github":"","twitter":"","stackoverflow":"","wechat":"","qq":"","weibo":"","zhihu":"","csdn":"","juejin":"","customs":{}}}}]}